{
  "name": "Cava",
  "summary": "Traditional method sparkling wine from Spain with fresh fruit and moderate complexity.",
  "regions": {
    "penedes": {
      "name": "Penedes",
      "climate": "Mediterranean",
      "styleSummary": "Fresh sparkling wines with citrus and apple notes.",
      "mitigating": ["altitude"],
      "grapes": {
        "Macabeo": {
          "style": "Citrus, apple, fresh.",
          "profile": {
            "acidity": "Medium to High",
            "alcohol": "Medium",
            "body": "Light",
            "tannin": "-"
          },
          "viticulture": ["Widely planted"],
          "winemaking": ["Traditional method"]
        },
        "Xarel-lo": {
          "style": "Structure, body.",
          "profile": {
            "acidity": "Medium",
            "alcohol": "Medium",
            "body": "Medium",
            "tannin": "-"
          },
          "viticulture": ["Adds body"],
          "winemaking": ["Blending grape"]
        },
        "Parellada": {
          "style": "Light, floral.",
          "profile": {
            "acidity": "High",
            "alcohol": "Low",
            "body": "Light",
            "tannin": "-"
          },
          "viticulture": ["High altitude"],
          "winemaking": ["Fresh styles"]
        }
      }
    }
  }
}